{
  "animateLoading": true,
  "borderRadius": "{{appsmith.theme.borderRadius.appBorderRadius}}",
  "bottomRow": 4,
  "boxShadow": "none",
  "buttonColor": "{{appsmith.theme.colors.primaryColor}}",
  "buttonVariant": "PRIMARY",
  "dynamicBindingPathList": [
    {
      "key": "buttonColor"
    },
    {
      "key": "borderRadius"
    }
  ],
  "dynamicTriggerPathList": [
    {
      "key": "onClick"
    }
  ],
  "iconName": "plus",
  "isDisabled": false,
  "isLoading": false,
  "isVisible": true,
  "key": "0fhm06tfya",
  "leftColumn": 60,
  "minWidth": 50,
  "mobileBottomRow": 36,
  "mobileLeftColumn": 19,
  "mobileRightColumn": 23,
  "mobileTopRow": 32,
  "needsErrorInfo": false,
  "onClick": "{{showModal(Modal1.name);}}",
  "parentColumnSpace": 19.15625,
  "parentId": "7ilyhtkq7c",
  "parentRowSpace": 10,
  "renderMode": "CANVAS",
  "responsiveBehavior": "hug",
  "rightColumn": 63,
  "topRow": 0,
  "type": "ICON_BUTTON_WIDGET",
  "version": 1,
  "widgetId": "2o42vk4ydf",
  "widgetName": "IconButton2"
}